computype/__init__.py
computype/computype.py
computype-0.0.4.dist-info/LICENSE
computype-0.0.4.dist-info/METADATA
computype-0.0.4.dist-info/WHEEL
computype-0.0.4.dist-info/top_level.txt
computype-0.0.4.dist-info/RECORD
